{
  "antiFeatures": {
    "NonFreeNet": {
      "apps": [
        "com.freetime.ssmpc"
      ]
    },
    "TetheredNet": {
      "apps": [
        "com.freetime.geoweather"
      ]
    }
  },
  "apksigner": "/home/Jamie/Android/Sdk/build-tools/37.0.0/apksigner",
  "archivePolicy0": [],
  "commandLine": [
    "/home/Jamie/.local/bin/fdroid update",
    "--pretty",
    "--delete-unknown"
  ],
  "disabled": [],
  "endTimestamp": 1779210355107,
  "failedBuilds": {
    "com.freetime.geoweather": [
      7,
      10,
      14,
      16,
      18,
      20,
      21,
      22,
      24,
      25,
      26,
      27,
      28,
      29,
      30,
      32,
      33,
      34,
      39,
      40,
      41,
      42,
      46,
      47,
      48,
      49,
      50
    ],
    "com.freetime.ssmpc": [
      11,
      12,
      13,
      14
    ]
  },
  "fdroiddata": {
    "commitId": "4fa4ec40b87ed7223bbbfb15e2afa3d42e619e49",
    "isDirty": true,
    "modifiedFiles": [
      "config.yml"
    ],
    "untrackedFiles": []
  },
  "jarsigner": "/usr/lib/jvm/java-21-openjdk-amd64/bin/jarsigner",
  "keytool": "/usr/lib/jvm/java-21-openjdk-amd64/bin/keytool",
  "needsUpdate": [],
  "noPackages": [],
  "noUpdateCheck": [],
  "stages": {
    "archive_old_apks archive": 1779210346320,
    "delete_disabled_builds": 1779210346316,
    "index.make archive": 1779210346321,
    "index.make repo": 1779210350911,
    "prepare_apps archive": 1779210346321,
    "prepare_apps repo": 1779210350869,
    "process_apks": 1779210346316,
    "read_added_date_from_all_apks": 1779210346319,
    "remove_apks": 1779210346319,
    "scan_repo_files": 1779210346318
  },
  "startTimestamp": 1779206746000,
  "subcommand": "update"
}